minio/__init__.py
minio/api.py
minio/compat.py
minio/copy_conditions.py
minio/definitions.py
minio/error.py
minio/fold_case_dict.py
minio/helpers.py
minio/parsers.py
minio/post_policy.py
minio/signer.py
minio/sse.py
minio/thread_pool.py
minio/xml_marshal.py
minio/credentials/__init__.py
minio/credentials/aws_iam.py
minio/credentials/chain.py
minio/credentials/credentials.py
minio/credentials/env_aws.py
minio/credentials/env_minio.py
minio/credentials/file_aws_credentials.py
minio/credentials/file_minio_client.py
minio/credentials/static.py
minio/select/__init__.py
minio/select/errors.py
minio/select/helpers.py
minio/select/options.py
minio/select/reader.py
ak_minio-5.0.7.post2.dist-info/LICENSE
ak_minio-5.0.7.post2.dist-info/METADATA
ak_minio-5.0.7.post2.dist-info/WHEEL
ak_minio-5.0.7.post2.dist-info/top_level.txt
ak_minio-5.0.7.post2.dist-info/RECORD
