Metadata-Version: 2.1
Name: ak-minio
Version: 5.0.7.post2
Summary: MinIO Python Library for Amazon S3 Compatible Cloud Storage for Python
Home-page: https://github.com/minio/minio-py
Author: MinIO, Inc.
Author-email: dev@min.io
License: Apache License 2.0
Download-URL: https://github.com/minio/minio-py
Platform: UNKNOWN
Classifier: Development Status :: 5 - Production/Stable
Classifier: Intended Audience :: Developers
Classifier: License :: OSI Approved :: Apache Software License
Classifier: Natural Language :: English
Classifier: Operating System :: OS Independent
Classifier: Programming Language :: Python
Classifier: Programming Language :: Python :: 2.7
Classifier: Programming Language :: Python :: 3.4
Classifier: Programming Language :: Python :: 3.5
Classifier: Programming Language :: Python :: 3.6
Classifier: Programming Language :: Python :: 3.7
Classifier: Topic :: Software Development :: Libraries :: Python Modules
Requires-Dist: urllib3
Requires-Dist: pytz
Requires-Dist: certifi
Requires-Dist: python-dateutil
Requires-Dist: configparser
Requires-Dist: future ; python_version < "3.0"
